microhttpx/__init__.py
microhttpx/logger.py
microhttpx/parser.py
microhttpx/request.py
microhttpx/response.py
microhttpx/server.py
microhttpx/status.py
microhttpx/structs.py
microhttpx-0.3.1.dist-info/licenses/LICENSE
microhttpx-0.3.1.dist-info/METADATA
microhttpx-0.3.1.dist-info/WHEEL
microhttpx-0.3.1.dist-info/top_level.txt
microhttpx-0.3.1.dist-info/RECORD
