Metadata-Version: 2.4
Name: microhttpx
Version: 0.3.1
Summary: Lightweight HTTP server library for microcontrollers.
Author: netcorelink
License: MIT
Project-URL: Homepage, https://github.com/netcorelink/microhttpx
Project-URL: Repository, https://github.com/netcorelink/microhttpx
Project-URL: Documentation, https://github.com/netcorelink/microhttpx#readme
Keywords: http,server,microcontroller,micropython,iot
Classifier: Programming Language :: Python :: 3
Classifier: Programming Language :: Python :: 3.8
Classifier: License :: OSI Approved :: MIT License
Classifier: Operating System :: OS Independent
Classifier: Intended Audience :: Developers
Classifier: Topic :: Internet :: WWW/HTTP :: HTTP Servers
Classifier: Typing :: Typed
Requires-Python: >=3.8
License-File: LICENSE
Dynamic: license-file
